LICENSE
README.md
pyproject.toml
setup.cfg
setup.py
releaserabbit/__init__.py
releaserabbit.egg-info/PKG-INFO
releaserabbit.egg-info/SOURCES.txt
releaserabbit.egg-info/dependency_links.txt
releaserabbit.egg-info/entry_points.txt
releaserabbit.egg-info/requires.txt
releaserabbit.egg-info/top_level.txt
tests/__init__.py
tests/test_component_bump.py